pyray/__init__.py
pyray/audio.py
pyray/axes.py
pyray/color.py
pyray/geometric.py
pyray/global_vars.py
pyray/grid.py
pyray/helpers.py
pyray/imageutils.py
pyray/misc.py
pyray/rotation.py
pyray/shapes/__init__.py
pyray/shapes/fourd/__init__.py
pyray/shapes/fourd/open_teserract.py
pyray/shapes/fourd/tesseract_graph.py
pyray/shapes/fourd/tst_open_tsrct.py
pyray/shapes/oned/__init__.py
pyray/shapes/oned/circle.py
pyray/shapes/oned/curve.py
pyray/shapes/solid/__init__.py
pyray/shapes/solid/cube.py
pyray/shapes/solid/open_cube.py
pyray/shapes/solid/open_cube_tst.py
pyray/shapes/solid/polyhedron.py
pyray/shapes/solid/sphere.py
pyray/shapes/solid/sphere_goldberg_132.py
pyray/shapes/solid/sphere_goldberg_252.py
pyray/shapes/twod/__init__.py
pyray/shapes/twod/functional.py
pyray/shapes/twod/line.py
pyray/shapes/twod/paraboloid.py
pyray/shapes/twod/plane.py
pyray/shapes/twod/plot.py
pyray/shapes/twod/square_mesh.py
pyray/shapes/twod/tst_sq_mesh.py
pyray/shapes/zerod/__init__.py
pyray/shapes/zerod/pointswarm.py
raypy-0.0.3.dist-info/LICENSE
raypy-0.0.3.dist-info/METADATA
raypy-0.0.3.dist-info/WHEEL
raypy-0.0.3.dist-info/top_level.txt
raypy-0.0.3.dist-info/RECORD
