Metadata-Version: 2.1
Name: raypy
Version: 0.0.3
Summary: A 3d rendering library written completely in python.
Home-page: https://github.com/ryu577/pyray
Author: Rohit Pandey
Author-email: rohitpandey576@gmail.com
License: MIT
Platform: UNKNOWN
Requires-Python: >=2.7, !=3.0.*, !=3.1.*, !=3.2.*, !=3.3.*, <4
Provides-Extra: dev
Provides-Extra: test
License-File: LICENSE
